LICENSE
MANIFEST.in
README.md
README.rst
setup.cfg
setup.py
FisherExact/Fisher.py
FisherExact/__init__.py
FisherExact.egg-info/PKG-INFO
FisherExact.egg-info/SOURCES.txt
FisherExact.egg-info/dependency_links.txt
FisherExact.egg-info/entry_points.txt
FisherExact.egg-info/requires.txt
FisherExact.egg-info/top_level.txt
FisherExact/statlib/FEXACT.F90
FisherExact/statlib/__init__.py
FisherExact/statlib/asa159.f90
FisherExact/statlib/asa205.f90
FisherExact/statlib/fexact-f2pywrappers2.f90
FisherExact/statlib/fexact.pyf
FisherExact/statlib/prterr.f
bin/fexact