Metadata-Version: 1.1
Name: FisherExact
Version: 1.4
Summary: Fishe's Exact test for mxn contingency table
Home-page: https://github.com/maclandrol/FisherExact
Author: Emmanuel Noutahi
Author-email: fmr.noutahi@umontreal.ca
License: GPL
Download-URL: https://github.com/maclandrol/FisherExact/archive/1.4.tar.gz
Keywords: statistic fisher independence test
Platform: UNKNOWN
Classifier: Development Status :: 4 - Beta
Classifier: Environment :: Console
Classifier: Natural Language :: English
Classifier: Intended Audience :: Developers
Classifier: Intended Audience :: Science/Research
Classifier: License :: OSI Approved :: GNU General Public License (GPL)
Classifier: Operating System :: Microsoft :: Windows
Classifier: Operating System :: POSIX
Classifier: Operating System :: Unix
Classifier: Operating System :: MacOS
Classifier: Programming Language :: Python
Classifier: Programming Language :: Python :: 2
Classifier: Programming Language :: Python :: 2.7
Classifier: Programming Language :: Python :: 3
Classifier: Programming Language :: Python :: 3.4
Classifier: Programming Language :: Python :: 3.5
Classifier: Programming Language :: Python :: 3.6
